trange/__init__.py
trange/trange.py
trange-0.1.1.dist-info/LICENSE
trange-0.1.1.dist-info/METADATA
trange-0.1.1.dist-info/WHEEL
trange-0.1.1.dist-info/top_level.txt
trange-0.1.1.dist-info/RECORD
