Metadata-Version: 2.1
Name: trange
Version: 0.1.1
Summary: A library for time ranges
Home-page: UNKNOWN
Author: UNKNOWN
Author-email: UNKNOWN
License: UNKNOWN
Platform: UNKNOWN
